minpin/minpin.py
minpin-1.0.0.dist-info/LICENSE.txt
minpin-1.0.0.dist-info/METADATA
minpin-1.0.0.dist-info/WHEEL
minpin-1.0.0.dist-info/entry_points.txt
minpin-1.0.0.dist-info/top_level.txt
minpin-1.0.0.dist-info/RECORD
