Metadata-Version: 2.1
Name: minpin
Version: 1.0.0
Summary: Automatically add minimum version pins to unpinned packages in conda YAML files.
Author-email: Demetris Roumis <8qdo8efl3@mozmail.com>
Keywords: conda,pinning,anaconda-project,dependencies
Classifier: Programming Language :: Python :: 3
Classifier: License :: OSI Approved :: BSD License
Classifier: Operating System :: OS Independent
Classifier: Topic :: Software Development :: Build Tools
Requires-Python: >=3.7
License-File: LICENSE.txt
Provides-Extra: test
Requires-Dist: pytest; extra == "test"
